LICENSE.txt
MANIFEST.in
rpa.py
setup.py
rpa.egg-info/PKG-INFO
rpa.egg-info/SOURCES.txt
rpa.egg-info/dependency_links.txt
rpa.egg-info/requires.txt
rpa.egg-info/top_level.txt